vaers_downloader/CaptchaReader.py
vaers_downloader/VAERSFileDownloader.py
vaers_downloader/WebDriver.py
vaers_downloader/__init__.py
vaers_downloader/download.py
vaers_downloader/metadata.py
vaers_downloader/zipUtils.py
vaers_downloader/model/keras_metadata.pb
vaers_downloader/model/saved_model.pb
vaers_downloader/model/variables/variables.data-00000-of-00001
vaers_downloader/model/variables/variables.index
vaers_downloader-1.0.2.dist-info/METADATA
vaers_downloader-1.0.2.dist-info/WHEEL
vaers_downloader-1.0.2.dist-info/licenses/AUTHORS
vaers_downloader-1.0.2.dist-info/licenses/LICENSE
vaers_downloader-1.0.2.dist-info/RECORD
