Metadata-Version: 2.1
Name: vaers-downloader
Version: 1.0.2
Summary: VAERS DATA DOWNLOADER
Project-URL: Homepage, https://github.com/McFlat/vaers-downloader
Project-URL: Bug Tracker, https://github.com/McFlat/vaers-downloader/issues
Author-email: Frank Knoll <Knoll_Frank@web.de>, Alex Goretoy <alex@goretoy.com>
License-File: AUTHORS
License-File: LICENSE
Classifier: Development Status :: 5 - Production/Stable
Classifier: Environment :: Console
Classifier: Intended Audience :: Healthcare Industry
Classifier: License :: OSI Approved :: MIT License
Classifier: Natural Language :: English
Classifier: Operating System :: OS Independent
Classifier: Programming Language :: Python :: 3
Classifier: Topic :: Utilities
Requires-Python: >=3.7
